odoo/addons/account_chart_update_l10n_eu_oss_oca/README.rst
odoo/addons/account_chart_update_l10n_eu_oss_oca/__init__.py
odoo/addons/account_chart_update_l10n_eu_oss_oca/__manifest__.py
odoo/addons/account_chart_update_l10n_eu_oss_oca/i18n/account_chart_update_l10n_eu_oss_oca.pot
odoo/addons/account_chart_update_l10n_eu_oss_oca/i18n/es.po
odoo/addons/account_chart_update_l10n_eu_oss_oca/i18n/it.po
odoo/addons/account_chart_update_l10n_eu_oss_oca/readme/CONTRIBUTORS.rst
odoo/addons/account_chart_update_l10n_eu_oss_oca/readme/DESCRIPTION.rst
odoo/addons/account_chart_update_l10n_eu_oss_oca/static/description/icon.png
odoo/addons/account_chart_update_l10n_eu_oss_oca/static/description/index.html
odoo/addons/account_chart_update_l10n_eu_oss_oca/tests/__init__.py
odoo/addons/account_chart_update_l10n_eu_oss_oca/tests/test_account_chart_update_l10n_eu_oss_oca.py
odoo/addons/account_chart_update_l10n_eu_oss_oca/wizard/__init__.py
odoo/addons/account_chart_update_l10n_eu_oss_oca/wizard/wizard_chart_update.py
odoo_addon_account_chart_update_l10n_eu_oss_oca-16.0.1.0.0.5.dist-info/METADATA
odoo_addon_account_chart_update_l10n_eu_oss_oca-16.0.1.0.0.5.dist-info/WHEEL
odoo_addon_account_chart_update_l10n_eu_oss_oca-16.0.1.0.0.5.dist-info/top_level.txt
odoo_addon_account_chart_update_l10n_eu_oss_oca-16.0.1.0.0.5.dist-info/RECORD
