Metadata-Version: 2.1
Name: odoo-addon-account-chart-update-l10n-eu-oss-oca
Version: 16.0.1.0.0.5
Summary: Account Chart update OSS OCA
Home-page: https://github.com/OCA/account-financial-tools
Author: ForgeFlow, Odoo Community Association (OCA)
Author-email: support@odoo-community.org
License: AGPL-3
Platform: UNKNOWN
Classifier: Programming Language :: Python
Classifier: Framework :: Odoo
Classifier: Framework :: Odoo :: 16.0
Classifier: License :: OSI Approved :: GNU Affero General Public License v3
Requires-Python: >=3.10
Requires-Dist: odoo-addon-account-chart-update <16.1dev,>=16.0dev
Requires-Dist: odoo-addon-l10n-eu-oss-oca <16.1dev,>=16.0dev
Requires-Dist: odoo <16.1dev,>=16.0a
